medic/__init__.py
medic/__main__.py
medic/cli/__init__.py
medic/cli/main.py
medic/conf/MetaboDashboardConfig.py
medic/conf/SupportedCV.py
medic/conf/SupportedModels.py
medic/conf/algo_sklearn.json
medic/conf/parameters.py
medic/domain/ClassificationDesign.py
medic/domain/DataMatrix.py
medic/domain/MetaData.py
medic/domain/MetaboController.py
medic/domain/MetaboExperiment.py
medic/domain/MetaboExperimentDTO.py
medic/domain/MetaboModel.py
medic/domain/ModelFactory.py
medic/domain/Results.py
medic/domain/SplitGroup.py
medic/domain/__init__.py
medic/domain/dumps/metadata/.gitkeep
medic/domain/dumps/splits/.gitkeep
medic/service/DataFormat.py
medic/service/ExperimentDesign.py
medic/service/LoggerConfig.py
medic/service/Plots.py
medic/service/RunMLalgo.py
medic/service/SamplesPairing.py
medic/service/Utils.py
medic/service/__init__.py
medic/service/moule_lago.py
medic/service/nbr_splits.py
medic/ui/__init__.py
medic/ui/app.py
medic/ui/assets/000_Stylesheet.css
medic/ui/assets/DecisionTree.png
medic/ui/assets/Figure_home_wider.png
medic/ui/assets/favicon.ico
medic/ui/assets/help_icon.png
medic/ui/assets/help_icon.svg
medic/ui/assets/update_figure_steps_MeDIC_4.svg
medic/ui/tabs/InfoTab.py
medic/ui/tabs/InterpretTab.py
medic/ui/tabs/MLTab.py
medic/ui/tabs/MetaTab.py
medic/ui/tabs/ResultsAggregatedTab.py
medic/ui/tabs/ResultsTab.py
medic/ui/tabs/SplitsTab.py
medic/ui/tabs/__init__.py
medic/ui/tabs/utils.py
medic_ml-1.0.0.dist-info/METADATA
medic_ml-1.0.0.dist-info/WHEEL
medic_ml-1.0.0.dist-info/entry_points.txt
medic_ml-1.0.0.dist-info/licenses/LICENSE
medic_ml-1.0.0.dist-info/RECORD
