Metadata-Version: 2.4
Name: medic-ml
Version: 1.0.0
Summary: Metabolomic Dashboard for Interpretable Classification
Project-URL: Homepage, https://elinaff.github.io/MeDIC/
Project-URL: Issues, https://github.com/ElinaFF/MeDIC/issues
Project-URL: Source, https://github.com/ElinaFF/MeDIC
Author-email: Elina Francovic-Fontaine <elina.francovic-fontaine.1@ulaval.ca>
License-File: LICENSE
Classifier: License :: OSI Approved :: MIT License
Classifier: Operating System :: OS Independent
Classifier: Programming Language :: Python :: 3
Requires-Python: <3.13,>=3.8
Requires-Dist: coloredlogs
Requires-Dist: dash
Requires-Dist: dash-bio
Requires-Dist: dash-bootstrap-components
Requires-Dist: dash-core-components
Requires-Dist: dash-cytoscape
Requires-Dist: dash-html-components
Requires-Dist: dash-interactive-graphviz
Requires-Dist: dash-renderer
Requires-Dist: dash-table
Requires-Dist: matplotlib
Requires-Dist: numba
Requires-Dist: numpy<2
Requires-Dist: openpyxl
Requires-Dist: pandas
Requires-Dist: plotly
Requires-Dist: pyscm-ml>=1.1.2
Requires-Dist: randomscm>=0.1.2
Requires-Dist: rich
Requires-Dist: scikit-learn>1.4
Requires-Dist: scipy
Requires-Dist: typer
Requires-Dist: umap-learn
Provides-Extra: dev
Requires-Dist: dash[testing]; extra == 'dev'
Requires-Dist: pytest; extra == 'dev'
